[
  {
    "name":"crown clothing",
    "id":1,
    "description":"an e-commerencial web where you can buy clothes",
    "url":"url"
  },
  {
    "name":"crown clothing",
    "id":2,
    "description":"an e-commerencial web where you can buy clothes",
    "url":"url"
  },
  {
    "name":"crown clothing",
    "id":3,
    "description":"an e-commerencial web where you can buy clothes",
    "url":"url"
  },
  {
    "name":"crown clothing",
    "id":4,
    "description":"an e-commerencial web where you can buy clothes",
    "url":"url"
  }
]